authenticator/__init__.py
simpl_authenticator-0.7.3.dist-info/METADATA
simpl_authenticator-0.7.3.dist-info/RECORD
simpl_authenticator-0.7.3.dist-info/WHEEL
simpl_authenticator-0.7.3.dist-info/top_level.txt
