Metadata-Version: 2.1
Name: simpl-authenticator
Version: 0.7.3
Summary: WAMP Authenticator Component for Simpl
Home-page: https://github.com/simplworld/simpl-authenticator
Author: UNKNOWN
Author-email: UNKNOWN
License: UNKNOWN
Platform: UNKNOWN
Classifier: Development Status :: 4 - Beta
Classifier: Environment :: Web Environment
Classifier: Intended Audience :: Developers
Classifier: License :: OSI Approved :: GNU General Public License v2 (GPLv2)
Classifier: Operating System :: OS Independent
Classifier: Programming Language :: Python :: 3
Requires-Dist: autobahn (==17.10.1)
